[
	{
		"name": "moliu",
		"avatar": "https://cdn.jsdelivr.net/gh/moliusmile/moliusmile.github.io/aboutme/Denise2.jpg",
		"link": "https://shuxinyang.com"
	},
	{
		"name": "miyehn",
		"avatar": "https://i.loli.net/2020/03/08/Gz8eBg1X7Zb6TWn.jpg",
		"link": "https://miyehn.me/blog"
	},
	{
		"name": "阿十九",
		"avatar": "https://cdn.jsdelivr.net/gh/ashijiu/ashijiu.github.io/images/mao.jpg",
		"link": "https://blog.ashijiu.com"
	},
	{
		"name": "枫糖",
		"avatar": "https://cdn.jsdelivr.net/gh/maplesugarr/blog-assets/imgs/maple-leaf-avatar.jpg",
		"link": "https://blog.maplesugar.space"
	},
	{
		"name": "元哥的日记",
		"avatar": "https://liyuanimage.oss-cn-beijing.aliyuncs.com/img/20191219220643.jpeg",
		"link": "https://leeee.top"
	},
	{
		"name": "Lan Ling",
		"avatar": "https://cdn.jsdelivr.net/gh/muyuuuu/muyuuuu.github.io/images/avatar.gif",
		"link": "https://muyuuuu.github.io"
	},
	{
		"name": "人间白玉楼",
		"avatar": "https://gallery.vksir.zone/images/2020/03/12/vksir.jpg",
		"link": "https://www.vksir.zone"
	},
	{
		"name": "荷戟独彷徨",
		"avatar": "https://cdn.jsdelivr.net/gh/guanqr/blog/static/icons/apple-touch-icon.png",
		"link": "https://guanqr.com"
	},
	{
		"name": "志军的博客",
		"avatar": "https://www.azjhong.com/images/hires_3769461-os.png",
		"link": "https://www.azjhong.com"
	},
	{
		"name": "米米的博客",
		"avatar": "https://gravatar.loli.net/avatar/f56980e9dc026727282a04eea02b4f4d?s=256",
		"link": "https://zhangshuqiao.org"
	},
	{
		"name": "ZZONN",
		"avatar": "https://cdn.jsdelivr.net/gh/lcorel/lcorel.github.io/images/avatar2.gif",
		"link": "https://blog.zzonn.com"
	},
	{
		"name": "Abalone",
		"avatar": "https://abalone.life/avatar",
		"link": "https://abalone.life"
	},
	{
		"name": "YD's blog",
		"avatar": "https://cdn.ydchen.cn/typora20200628094101.jpg",
		"link": "https://ydchen.cn"
	},
	{
		"name": "先谢郭嘉",
		"avatar": "https://cdn.jsdelivr.net/gh/xiejiabin1/images/favicon.jpg",
		"link": "https://xiejiabin.online"
	},
	{
		"name": "Willow の空间",
		"avatar": "https://unsplash.it/100/100?image=1005",
		"link": "http://blog.haozz.site"
	},
	{
		"name": "Ljcbaby 的小屋",
		"avatar": "https://cdn.jsdelivr.net/gh/ljcbaby/Static/logo/0.png",
		"link": "https://www.ljcbaby.top"
	},
	{
		"name": "Daman's Blog",
		"avatar": "https://ae01.alicdn.com/kf/U2ebdbb0ad7c84a9695715a75e3b7359ec.jpg",
		"link": "https://www.damanyang.cn"
	}
]